{
  "headers": {
    "date": "Mon, 12 Aug 2024 04:40:34 GMT",
    "x-amz-cf-id": "iIfSn6Fd2ahBTUUIWGyJBihuWpodabLvshEzLxUwAQHSdP1NrsUH8A==",
    "etag": "W/\"8b36c43088485ca65c5fe5430fa16482\"",
    "x-amz-version-id": "bWdhsv72FJwkoCrNOIiBoRJdsMBWLDeg",
    "content-type": "application/javascript",
    "x-cache": "Hit from cloudfront",
    "via": "http/2 edgeproxy-h",
    "access-control-allow-origin": "*",
    "vary": "Accept-Encoding, Origin",
    "x-amz-cf-pop": "FRA56-P5",
    "x-amz-replication-status": "COMPLETED",
    "referrer-policy": "strict-origin-when-cross-origin",
    "content-security-policy": "default-src 'none'; style-src 'unsafe-inline'; sandbox",
    "x-content-type-options": "nosniff",
    "cross-origin-resource-policy": "same-origin",
    "cache-control": "public, max-age=31536000, immutable",
    "x-frame-options": "DENY",
    "server-timing": "fetchSource;dur=10",
    "cross-origin-embedder-policy": "same-origin",
    "cross-origin-opener-policy": "same-origin",
    "server": "deno/gcp-europe-west3",
    "last-modified": "Fri, 25 Mar 2022 13:32:48 GMT",
    "strict-transport-security": "max-age=63072000; includeSubDomains; preload",
    "age": "4516490"
  },
  "url": "https://deno.land/std@0.132.0/node/_crypto/crypto_browserify/browserify_aes/modes/ctr.js",
  "now": {
    "secs_since_epoch": 1727954123,
    "nanos_since_epoch": 89307134
  }
}